{"font":"QCF4_Hafs_06","lines":[{"n":1,"w":[{"c":"пҸў","v":"3:174"},{"c":"пҸЈ","v":"3:174"},{"c":"пҸӨ","v":"3:174"},{"c":"пҸҘ","v":"3:174"},{"c":"пҸҰ","v":"3:174"},{"c":"пҸ§","v":"3:174"},{"c":"пҸЁ","v":"3:174"},{"c":"пҸ©","v":"3:174"},{"c":"пҸӘ","v":"3:174"}]},{"n":2,"w":[{"c":"пҸ«","v":"3:174"},{"c":"пҸ¬","v":"3:174"},{"c":"пҸ®","v":"3:174"},{"c":"пҸҜ","v":"3:174"},{"c":"пҸ°","v":"3:174"},{"c":"пҸұ","v":"3:174"},{"c":"пҸІ","v":"3:174","e":1},{"c":"пҸі","v":"3:175"},{"c":"пҸҙ","v":"3:175"},{"c":"пҸө","v":"3:175"}]},{"n":3,"w":[{"c":"пҸ¶","v":"3:175"},{"c":"пҸ·","v":"3:175"},{"c":"пҸё","v":"3:175"},{"c":"пҸ№","v":"3:175"},{"c":"пҸә","v":"3:175"},{"c":"пҸ»","v":"3:175"},{"c":"пҸј","v":"3:175"},{"c":"пҸҪ","v":"3:175"},{"c":"пҸҫ","v":"3:175","e":1}]},{"n":4,"w":[{"c":"пҸҝ","v":"3:176"},{"c":"пҗҖ","v":"3:176"},{"c":"пҗҒ","v":"3:176"},{"c":"пҗӮ","v":"3:176"},{"c":"пҗғ","v":"3:176"},{"c":"пҗ„","v":"3:176"},{"c":"пҗҶ","v":"3:176"},{"c":"пҗҮ","v":"3:176"},{"c":"пҗҲ","v":"3:176"},{"c":"пҗү","v":"3:176"}]},{"n":5,"w":[{"c":"пҗҠ","v":"3:176"},{"c":"пҗҢ","v":"3:176"},{"c":"пҗҚ","v":"3:176"},{"c":"пҗҺ","v":"3:176"},{"c":"пҗҸ","v":"3:176"},{"c":"пҗҗ","v":"3:176"},{"c":"пҗ‘","v":"3:176"},{"c":"пҗ’","v":"3:176"},{"c":"пҗ“","v":"3:176"},{"c":"пҗ•","v":"3:176"},{"c":"пҗ–","v":"3:176"}]},{"n":6,"w":[{"c":"пҗ—","v":"3:176"},{"c":"пҗҳ","v":"3:176","e":1},{"c":"пҗҷ","v":"3:177"},{"c":"пҗҡ","v":"3:177"},{"c":"пҗӣ","v":"3:177"},{"c":"пҗң","v":"3:177"},{"c":"пҗқ","v":"3:177"},{"c":"пҗһ","v":"3:177"},{"c":"пҗҹ","v":"3:177"},{"c":"пҗ ","v":"3:177"}]},{"n":7,"w":[{"c":"пҗЎ","v":"3:177"},{"c":"пҗЈ","v":"3:177"},{"c":"пҗӨ","v":"3:177"},{"c":"пҗҘ","v":"3:177"},{"c":"пҗҰ","v":"3:177","e":1},{"c":"пҗ§","v":"3:178"},{"c":"пҗЁ","v":"3:178"},{"c":"пҗ©","v":"3:178"},{"c":"пҗӘ","v":"3:178"},{"c":"пҗ«","v":"3:178"}]},{"n":8,"w":[{"c":"пҗ¬","v":"3:178"},{"c":"пҗӯ","v":"3:178"},{"c":"пҗ®","v":"3:178"},{"c":"пҗҜ","v":"3:178"},{"c":"пҗұ","v":"3:178"},{"c":"пҗІ","v":"3:178"},{"c":"пҗі","v":"3:178"},{"c":"пҗҙ","v":"3:178"},{"c":"пҗө","v":"3:178"},{"c":"пҗ·","v":"3:178"}]},{"n":9,"w":[{"c":"пҗё","v":"3:178"},{"c":"пҗ№","v":"3:178"},{"c":"пҗә","v":"3:178","e":1},{"c":"пҗ»","v":"3:179"},{"c":"пҗј","v":"3:179"},{"c":"пҗҪ","v":"3:179"},{"c":"пҗҫ","v":"3:179"},{"c":"пҗҝ","v":"3:179"},{"c":"п‘Җ","v":"3:179"},{"c":"п‘Ғ","v":"3:179"},{"c":"п‘Ӯ","v":"3:179"}]},{"n":10,"w":[{"c":"п‘ғ","v":"3:179"},{"c":"п‘„","v":"3:179"},{"c":"п‘…","v":"3:179"},{"c":"п‘Ҷ","v":"3:179"},{"c":"п‘Ү","v":"3:179"},{"c":"п‘Ҳ","v":"3:179"},{"c":"п‘Ҡ","v":"3:179"},{"c":"п‘Ӣ","v":"3:179"},{"c":"п‘Ң","v":"3:179"},{"c":"п‘Қ","v":"3:179"}]},{"n":11,"w":[{"c":"п‘Һ","v":"3:179"},{"c":"п‘Ҹ","v":"3:179"},{"c":"п‘җ","v":"3:179"},{"c":"п‘‘","v":"3:179"},{"c":"п‘’","v":"3:179"},{"c":"п‘“","v":"3:179"},{"c":"п‘”","v":"3:179"},{"c":"п‘•","v":"3:179"},{"c":"п‘–","v":"3:179"},{"c":"п‘ҳ","v":"3:179"},{"c":"п‘ҷ","v":"3:179"}]},{"n":12,"w":[{"c":"п‘ҡ","v":"3:179"},{"c":"п‘ң","v":"3:179"},{"c":"п‘қ","v":"3:179"},{"c":"п‘һ","v":"3:179"},{"c":"п‘ҹ","v":"3:179"},{"c":"п‘ ","v":"3:179"},{"c":"п‘Ў","v":"3:179"},{"c":"п‘ў","v":"3:179","e":1},{"c":"п‘Ј","v":"3:180"},{"c":"п‘Ө","v":"3:180"}]},{"n":13,"w":[{"c":"п‘Ҙ","v":"3:180"},{"c":"п‘Ұ","v":"3:180"},{"c":"п‘§","v":"3:180"},{"c":"п‘Ё","v":"3:180"},{"c":"п‘©","v":"3:180"},{"c":"п‘Ә","v":"3:180"},{"c":"п‘«","v":"3:180"},{"c":"п‘¬","v":"3:180"},{"c":"п‘ӯ","v":"3:180"},{"c":"п‘®","v":"3:180"}]},{"n":14,"w":[{"c":"п‘°","v":"3:180"},{"c":"п‘ұ","v":"3:180"},{"c":"п‘І","v":"3:180"},{"c":"п‘і","v":"3:180"},{"c":"п‘ө","v":"3:180"},{"c":"п‘¶","v":"3:180"},{"c":"п‘·","v":"3:180"},{"c":"п‘ё","v":"3:180"},{"c":"п‘№","v":"3:180"},{"c":"п‘ә","v":"3:180"},{"c":"п‘ј","v":"3:180"}]},{"n":15,"w":[{"c":"п‘Ҫ","v":"3:180"},{"c":"п‘ҫ","v":"3:180"},{"c":"п‘ҝ","v":"3:180"},{"c":"п’Ғ","v":"3:180"},{"c":"п’Ӯ","v":"3:180"},{"c":"п’ғ","v":"3:180"},{"c":"п’„","v":"3:180"},{"c":"п’…","v":"3:180","e":1}]}]}