{"font":"QCF4_Hafs_20","lines":[{"n":1,"w":[{"c":"пҹғ","v":"15:52"},{"c":"пҹ„","v":"15:52"},{"c":"пҹ…","v":"15:52"},{"c":"пҹҶ","v":"15:52"},{"c":"пҹҮ","v":"15:52"},{"c":"пҹҲ","v":"15:52"},{"c":"пҹү","v":"15:52"},{"c":"пҹҠ","v":"15:52"},{"c":"пҹӢ","v":"15:52"},{"c":"пҹҢ","v":"15:52","e":1},{"c":"пҹҚ","v":"15:53"}]},{"n":2,"w":[{"c":"пҹҺ","v":"15:53"},{"c":"пҹҸ","v":"15:53"},{"c":"пҹҗ","v":"15:53"},{"c":"пҹ‘","v":"15:53"},{"c":"пҹ’","v":"15:53"},{"c":"пҹ“","v":"15:53"},{"c":"пҹ”","v":"15:53","e":1},{"c":"пҹ•","v":"15:54"},{"c":"пҹ–","v":"15:54"},{"c":"пҹ—","v":"15:54"},{"c":"пҹҳ","v":"15:54"}]},{"n":3,"w":[{"c":"пҹҷ","v":"15:54"},{"c":"пҹҡ","v":"15:54"},{"c":"пҹӣ","v":"15:54"},{"c":"пҹң","v":"15:54"},{"c":"пҹқ","v":"15:54","e":1},{"c":"пҹһ","v":"15:55"},{"c":"пҹҹ","v":"15:55"},{"c":"пҹ ","v":"15:55"}]},{"n":4,"w":[{"c":"пҹЎ","v":"15:55"},{"c":"пҹў","v":"15:55"},{"c":"пҹЈ","v":"15:55"},{"c":"пҹӨ","v":"15:55"},{"c":"пҹҘ","v":"15:55","e":1},{"c":"пҹҰ","v":"15:56"},{"c":"пҹ§","v":"15:56"},{"c":"пҹЁ","v":"15:56"},{"c":"пҹ©","v":"15:56"},{"c":"пҹӘ","v":"15:56"}]},{"n":5,"w":[{"c":"пҹ«","v":"15:56"},{"c":"пҹ¬","v":"15:56"},{"c":"пҹӯ","v":"15:56"},{"c":"пҹ®","v":"15:56","e":1},{"c":"пҹҜ","v":"15:57"},{"c":"пҹ°","v":"15:57"},{"c":"пҹұ","v":"15:57"},{"c":"пҹІ","v":"15:57"},{"c":"пҹі","v":"15:57"},{"c":"пҹҙ","v":"15:57","e":1}]},{"n":6,"w":[{"c":"пҹө","v":"15:58"},{"c":"пҹ¶","v":"15:58"},{"c":"пҹ·","v":"15:58"},{"c":"пҹё","v":"15:58"},{"c":"пҹ№","v":"15:58"},{"c":"пҹә","v":"15:58"},{"c":"пҹ»","v":"15:58","e":1},{"c":"пҹј","v":"15:59"},{"c":"пҹҪ","v":"15:59"},{"c":"пҹҫ","v":"15:59"}]},{"n":7,"w":[{"c":"пҹҝ","v":"15:59"},{"c":"п Җ","v":"15:59"},{"c":"п Ғ","v":"15:59"},{"c":"п Ӯ","v":"15:59","e":1},{"c":"п ғ","v":"15:60"},{"c":"п „","v":"15:60"},{"c":"п …","v":"15:60"},{"c":"п Ҷ","v":"15:60"},{"c":"п Ү","v":"15:60"}]},{"n":8,"w":[{"c":"п Ҳ","v":"15:60"},{"c":"п ү","v":"15:60","e":1},{"c":"п Ҡ","v":"15:61"},{"c":"п Ӣ","v":"15:61"},{"c":"п Ң","v":"15:61"},{"c":"п Қ","v":"15:61"},{"c":"п Һ","v":"15:61"},{"c":"п Ҹ","v":"15:61","e":1},{"c":"п җ","v":"15:62"}]},{"n":9,"w":[{"c":"п ‘","v":"15:62"},{"c":"п ’","v":"15:62"},{"c":"п “","v":"15:62"},{"c":"п ”","v":"15:62","e":1},{"c":"п •","v":"15:63"},{"c":"п –","v":"15:63"},{"c":"п —","v":"15:63"},{"c":"п ҳ","v":"15:63"},{"c":"п ҷ","v":"15:63"},{"c":"п ҡ","v":"15:63"}]},{"n":10,"w":[{"c":"п ӣ","v":"15:63"},{"c":"п ң","v":"15:63","e":1},{"c":"п қ","v":"15:64"},{"c":"п һ","v":"15:64"},{"c":"п ҹ","v":"15:64"},{"c":"п  ","v":"15:64"},{"c":"п Ў","v":"15:64","e":1},{"c":"п ў","v":"15:65"}]},{"n":11,"w":[{"c":"п Ј","v":"15:65"},{"c":"п Ө","v":"15:65"},{"c":"п Ҙ","v":"15:65"},{"c":"п Ұ","v":"15:65"},{"c":"п §","v":"15:65"},{"c":"п Ё","v":"15:65"},{"c":"п ©","v":"15:65"},{"c":"п Ә","v":"15:65"},{"c":"п «","v":"15:65"},{"c":"п ¬","v":"15:65"}]},{"n":12,"w":[{"c":"п ӯ","v":"15:65"},{"c":"п ®","v":"15:65"},{"c":"п Ҝ","v":"15:65"},{"c":"п °","v":"15:65","e":1},{"c":"п ұ","v":"15:66"},{"c":"п І","v":"15:66"},{"c":"п і","v":"15:66"},{"c":"п ҙ","v":"15:66"},{"c":"п ө","v":"15:66"}]},{"n":13,"w":[{"c":"п ¶","v":"15:66"},{"c":"п ·","v":"15:66"},{"c":"п ё","v":"15:66"},{"c":"п №","v":"15:66"},{"c":"п ә","v":"15:66","e":1},{"c":"п »","v":"15:67"},{"c":"п ј","v":"15:67"},{"c":"п Ҫ","v":"15:67"}]},{"n":14,"w":[{"c":"п ҫ","v":"15:67"},{"c":"п ҝ","v":"15:67","e":1},{"c":"пЎҖ","v":"15:68"},{"c":"пЎҒ","v":"15:68"},{"c":"пЎӮ","v":"15:68"},{"c":"пЎғ","v":"15:68"},{"c":"пЎ„","v":"15:68"},{"c":"пЎ…","v":"15:68"},{"c":"пЎҶ","v":"15:68","e":1}]},{"n":15,"w":[{"c":"пЎҮ","v":"15:69"},{"c":"пЎҲ","v":"15:69"},{"c":"пЎү","v":"15:69"},{"c":"пЎҠ","v":"15:69"},{"c":"пЎӢ","v":"15:69","e":1},{"c":"пЎҢ","v":"15:70"},{"c":"пЎҚ","v":"15:70"},{"c":"пЎҺ","v":"15:70"},{"c":"пЎҸ","v":"15:70"},{"c":"пЎҗ","v":"15:70"},{"c":"пЎ‘","v":"15:70","e":1}]}]}