{"font":"QCF4_Hafs_04","lines":[{"n":1,"w":[{"c":"пқ“","v":"3:23"},{"c":"пқ”","v":"3:23"},{"c":"пқ•","v":"3:23"},{"c":"пқ–","v":"3:23"},{"c":"пқ—","v":"3:23"},{"c":"пқҳ","v":"3:23"},{"c":"пқҷ","v":"3:23"},{"c":"пқҡ","v":"3:23"},{"c":"пқӣ","v":"3:23"},{"c":"пқң","v":"3:23"},{"c":"пққ","v":"3:23"}]},{"n":2,"w":[{"c":"пқһ","v":"3:23"},{"c":"пқҹ","v":"3:23"},{"c":"пқ ","v":"3:23"},{"c":"пқЎ","v":"3:23"},{"c":"пқў","v":"3:23"},{"c":"пқЈ","v":"3:23"},{"c":"пқӨ","v":"3:23"},{"c":"пқҘ","v":"3:23"},{"c":"пқҰ","v":"3:23"},{"c":"пқ§","v":"3:23","e":1}]},{"n":3,"w":[{"c":"пқЁ","v":"3:24"},{"c":"пқ©","v":"3:24"},{"c":"пқӘ","v":"3:24"},{"c":"пқ«","v":"3:24"},{"c":"пқ¬","v":"3:24"},{"c":"пқӯ","v":"3:24"},{"c":"пқ®","v":"3:24"},{"c":"пқҜ","v":"3:24"},{"c":"пқ°","v":"3:24"}]},{"n":4,"w":[{"c":"пқІ","v":"3:24"},{"c":"пқі","v":"3:24"},{"c":"пқҙ","v":"3:24"},{"c":"пқө","v":"3:24"},{"c":"пқ¶","v":"3:24"},{"c":"пқ·","v":"3:24"},{"c":"пқё","v":"3:24","e":1},{"c":"пқ№","v":"3:25"},{"c":"пқә","v":"3:25"},{"c":"пқ»","v":"3:25"}]},{"n":5,"w":[{"c":"пқј","v":"3:25"},{"c":"пқҪ","v":"3:25"},{"c":"пқҫ","v":"3:25"},{"c":"пқҝ","v":"3:25"},{"c":"пһҖ","v":"3:25"},{"c":"пһҒ","v":"3:25"},{"c":"пһӮ","v":"3:25"},{"c":"пһғ","v":"3:25"},{"c":"пһ„","v":"3:25"},{"c":"пһ…","v":"3:25"}]},{"n":6,"w":[{"c":"пһҶ","v":"3:25"},{"c":"пһҮ","v":"3:25"},{"c":"пһҲ","v":"3:25","e":1},{"c":"пһү","v":"3:26"},{"c":"пһҠ","v":"3:26"},{"c":"пһӢ","v":"3:26"},{"c":"пһҢ","v":"3:26"},{"c":"пһҚ","v":"3:26"},{"c":"пһҺ","v":"3:26"},{"c":"пһҸ","v":"3:26"}]},{"n":7,"w":[{"c":"пһҗ","v":"3:26"},{"c":"пһ‘","v":"3:26"},{"c":"пһ’","v":"3:26"},{"c":"пһ“","v":"3:26"},{"c":"пһ”","v":"3:26"},{"c":"пһ•","v":"3:26"},{"c":"пһ–","v":"3:26"},{"c":"пһ—","v":"3:26"},{"c":"пһҳ","v":"3:26"},{"c":"пһҷ","v":"3:26"}]},{"n":8,"w":[{"c":"пһҡ","v":"3:26"},{"c":"пһң","v":"3:26"},{"c":"пһқ","v":"3:26"},{"c":"пһҹ","v":"3:26"},{"c":"пһ ","v":"3:26"},{"c":"пһЎ","v":"3:26"},{"c":"пһў","v":"3:26"},{"c":"пһЈ","v":"3:26"},{"c":"пһӨ","v":"3:26","e":1},{"c":"пһҘ","v":"3:27"},{"c":"пһҰ","v":"3:27"}]},{"n":9,"w":[{"c":"пһ§","v":"3:27"},{"c":"пһЁ","v":"3:27"},{"c":"пһ©","v":"3:27"},{"c":"пһӘ","v":"3:27"},{"c":"пһ«","v":"3:27"},{"c":"пһ¬","v":"3:27"},{"c":"пһ®","v":"3:27"},{"c":"пһҜ","v":"3:27"},{"c":"пһ°","v":"3:27"},{"c":"пһұ","v":"3:27"}]},{"n":10,"w":[{"c":"пһІ","v":"3:27"},{"c":"пһі","v":"3:27"},{"c":"пһҙ","v":"3:27"},{"c":"пһө","v":"3:27"},{"c":"пһ·","v":"3:27"},{"c":"пһё","v":"3:27"},{"c":"пһ№","v":"3:27"},{"c":"пһә","v":"3:27"},{"c":"пһ»","v":"3:27"},{"c":"пһј","v":"3:27","e":1}]},{"n":11,"w":[{"c":"пһҪ","v":"3:28"},{"c":"пһҫ","v":"3:28"},{"c":"пһҝ","v":"3:28"},{"c":"пҹҖ","v":"3:28"},{"c":"пҹҒ","v":"3:28"},{"c":"пҹӮ","v":"3:28"},{"c":"пҹғ","v":"3:28"},{"c":"пҹ„","v":"3:28"}]},{"n":12,"w":[{"c":"пҹҶ","v":"3:28"},{"c":"пҹҮ","v":"3:28"},{"c":"пҹҲ","v":"3:28"},{"c":"пҹү","v":"3:28"},{"c":"пҹҠ","v":"3:28"},{"c":"пҹӢ","v":"3:28"},{"c":"пҹҢ","v":"3:28"},{"c":"пҹҚ","v":"3:28"},{"c":"пҹҺ","v":"3:28"},{"c":"пҹҸ","v":"3:28"},{"c":"пҹҗ","v":"3:28"},{"c":"пҹ‘","v":"3:28"}]},{"n":13,"w":[{"c":"пҹ’","v":"3:28"},{"c":"пҹ”","v":"3:28"},{"c":"пҹ•","v":"3:28"},{"c":"пҹ–","v":"3:28"},{"c":"пҹҳ","v":"3:28"},{"c":"пҹҷ","v":"3:28"},{"c":"пҹҡ","v":"3:28"},{"c":"пҹӣ","v":"3:28","e":1},{"c":"пҹң","v":"3:29"}]},{"n":14,"w":[{"c":"пҹқ","v":"3:29"},{"c":"пҹһ","v":"3:29"},{"c":"пҹҹ","v":"3:29"},{"c":"пҹ ","v":"3:29"},{"c":"пҹЎ","v":"3:29"},{"c":"пҹў","v":"3:29"},{"c":"пҹЈ","v":"3:29"},{"c":"пҹӨ","v":"3:29"},{"c":"пҹҘ","v":"3:29"},{"c":"пҹ§","v":"3:29"}]},{"n":15,"w":[{"c":"пҹЁ","v":"3:29"},{"c":"пҹ©","v":"3:29"},{"c":"пҹӘ","v":"3:29"},{"c":"пҹ«","v":"3:29"},{"c":"пҹ¬","v":"3:29"},{"c":"пҹӯ","v":"3:29"},{"c":"пҹҜ","v":"3:29"},{"c":"пҹ°","v":"3:29"},{"c":"пҹұ","v":"3:29"},{"c":"пҹІ","v":"3:29"},{"c":"пҹі","v":"3:29"},{"c":"пҹҙ","v":"3:29","e":1}]}]}