{"font":"QCF4_Hafs_06","lines":[{"n":1,"w":[{"c":"п’Ҷ","v":"3:181"},{"c":"п’Ү","v":"3:181"},{"c":"п’Ҳ","v":"3:181"},{"c":"п’ү","v":"3:181"},{"c":"п’Ҡ","v":"3:181"},{"c":"п’Ӣ","v":"3:181"},{"c":"п’Ң","v":"3:181"},{"c":"п’Қ","v":"3:181"},{"c":"п’Һ","v":"3:181"},{"c":"п’Ҹ","v":"3:181"},{"c":"п’җ","v":"3:181"}]},{"n":2,"w":[{"c":"п’’","v":"3:181"},{"c":"п’“","v":"3:181"},{"c":"п’”","v":"3:181"},{"c":"п’•","v":"3:181"},{"c":"п’–","v":"3:181"},{"c":"п’—","v":"3:181"},{"c":"п’ҳ","v":"3:181"},{"c":"п’ҷ","v":"3:181"}]},{"n":3,"w":[{"c":"п’ҡ","v":"3:181"},{"c":"п’ӣ","v":"3:181"},{"c":"п’ң","v":"3:181"},{"c":"п’қ","v":"3:181","e":1},{"c":"п’һ","v":"3:182"},{"c":"п’ҹ","v":"3:182"},{"c":"п’ ","v":"3:182"},{"c":"п’Ў","v":"3:182"}]},{"n":4,"w":[{"c":"п’ў","v":"3:182"},{"c":"п’Ј","v":"3:182"},{"c":"п’Ө","v":"3:182"},{"c":"п’Ҙ","v":"3:182"},{"c":"п’Ұ","v":"3:182"},{"c":"п’§","v":"3:182","e":1},{"c":"п’Ё","v":"3:183"},{"c":"п’©","v":"3:183"},{"c":"п’Ә","v":"3:183"},{"c":"п’«","v":"3:183"}]},{"n":5,"w":[{"c":"п’¬","v":"3:183"},{"c":"п’ӯ","v":"3:183"},{"c":"п’®","v":"3:183"},{"c":"п’Ҝ","v":"3:183"},{"c":"п’°","v":"3:183"},{"c":"п’ұ","v":"3:183"},{"c":"п’І","v":"3:183"},{"c":"п’і","v":"3:183"}]},{"n":6,"w":[{"c":"п’ҙ","v":"3:183"},{"c":"п’ө","v":"3:183"},{"c":"п’·","v":"3:183"},{"c":"п’ё","v":"3:183"},{"c":"п’№","v":"3:183"},{"c":"п’ә","v":"3:183"},{"c":"п’»","v":"3:183"},{"c":"п’ј","v":"3:183"},{"c":"п’Ҫ","v":"3:183"}]},{"n":7,"w":[{"c":"п’ҫ","v":"3:183"},{"c":"п’ҝ","v":"3:183"},{"c":"п“Җ","v":"3:183"},{"c":"п“Ғ","v":"3:183"},{"c":"п“Ӯ","v":"3:183"},{"c":"п“ғ","v":"3:183"},{"c":"п“„","v":"3:183"},{"c":"п“…","v":"3:183","e":1}]},{"n":8,"w":[{"c":"п“Ҷ","v":"3:184"},{"c":"п“Ү","v":"3:184"},{"c":"п“Ҳ","v":"3:184"},{"c":"п“ү","v":"3:184"},{"c":"п“Ҡ","v":"3:184"},{"c":"п“Ӣ","v":"3:184"},{"c":"п“Ң","v":"3:184"},{"c":"п“Қ","v":"3:184"}]},{"n":9,"w":[{"c":"п“Һ","v":"3:184"},{"c":"п“Ҹ","v":"3:184"},{"c":"п“җ","v":"3:184"},{"c":"п“‘","v":"3:184"},{"c":"п“’","v":"3:184","e":1},{"c":"п““","v":"3:185"},{"c":"п“”","v":"3:185"}]},{"n":10,"w":[{"c":"п“•","v":"3:185"},{"c":"п“–","v":"3:185"},{"c":"п“ҳ","v":"3:185"},{"c":"п“ҷ","v":"3:185"},{"c":"п“ҡ","v":"3:185"},{"c":"п“ӣ","v":"3:185"},{"c":"п“ң","v":"3:185"}]},{"n":11,"w":[{"c":"п“һ","v":"3:185"},{"c":"п“ҹ","v":"3:185"},{"c":"п“ ","v":"3:185"},{"c":"п“Ў","v":"3:185"},{"c":"п“ў","v":"3:185"},{"c":"п“Ј","v":"3:185"},{"c":"п“Ө","v":"3:185"},{"c":"п“Ҙ","v":"3:185"},{"c":"п“§","v":"3:185"}]},{"n":12,"w":[{"c":"п“Ё","v":"3:185"},{"c":"п“©","v":"3:185"},{"c":"п“Ә","v":"3:185"},{"c":"п“«","v":"3:185"},{"c":"п“¬","v":"3:185"},{"c":"п“ӯ","v":"3:185","e":1},{"c":"п“®","v":"3:186","q":1},{"c":"п“Ҝ","v":"3:186"},{"c":"п“°","v":"3:186"}]},{"n":13,"w":[{"c":"п“ұ","v":"3:186"},{"c":"п“І","v":"3:186"},{"c":"п“і","v":"3:186"},{"c":"п“ҙ","v":"3:186"},{"c":"п“ө","v":"3:186"},{"c":"п“¶","v":"3:186"}]},{"n":14,"w":[{"c":"п“·","v":"3:186"},{"c":"п“ё","v":"3:186"},{"c":"п“№","v":"3:186"},{"c":"п“ә","v":"3:186"},{"c":"п“»","v":"3:186"},{"c":"п“ј","v":"3:186"},{"c":"п“Ҫ","v":"3:186"},{"c":"п“ҫ","v":"3:186"}]},{"n":15,"w":[{"c":"п”Җ","v":"3:186"},{"c":"п”Ғ","v":"3:186"},{"c":"п”Ӯ","v":"3:186"},{"c":"п”ғ","v":"3:186"},{"c":"п”„","v":"3:186"},{"c":"п”…","v":"3:186"},{"c":"п”Ҷ","v":"3:186"},{"c":"п”Ү","v":"3:186"},{"c":"п”Ҳ","v":"3:186","e":1}]}]}