{"font":"QCF4_Hafs_14","lines":[{"n":1,"w":[{"c":"п„Җ","v":"7:179"},{"c":"п„Ғ","v":"7:179"},{"c":"п„Ӯ","v":"7:179"},{"c":"п„ғ","v":"7:179"},{"c":"п„„","v":"7:179"},{"c":"п„…","v":"7:179"},{"c":"п„Ҷ","v":"7:179"},{"c":"п„Ҳ","v":"7:179"},{"c":"п„ү","v":"7:179"},{"c":"п„Ҡ","v":"7:179"},{"c":"п„Ӣ","v":"7:179"}]},{"n":2,"w":[{"c":"п„Ң","v":"7:179"},{"c":"п„Қ","v":"7:179"},{"c":"п„Һ","v":"7:179"},{"c":"п„Ҹ","v":"7:179"},{"c":"п„җ","v":"7:179"},{"c":"п„‘","v":"7:179"},{"c":"п„’","v":"7:179"},{"c":"п„“","v":"7:179"},{"c":"п„”","v":"7:179"},{"c":"п„•","v":"7:179"},{"c":"п„–","v":"7:179"}]},{"n":3,"w":[{"c":"п„ҳ","v":"7:179"},{"c":"п„ҷ","v":"7:179"},{"c":"п„ҡ","v":"7:179"},{"c":"п„ӣ","v":"7:179"},{"c":"п„ң","v":"7:179"},{"c":"п„һ","v":"7:179"},{"c":"п„ҹ","v":"7:179"},{"c":"п„ ","v":"7:179"},{"c":"п„Ў","v":"7:179","e":1},{"c":"п„ў","v":"7:180"}]},{"n":4,"w":[{"c":"п„Ј","v":"7:180"},{"c":"п„Ө","v":"7:180"},{"c":"п„Ҙ","v":"7:180"},{"c":"п„Ұ","v":"7:180"},{"c":"п„Ё","v":"7:180"},{"c":"п„©","v":"7:180"},{"c":"п„Ә","v":"7:180"},{"c":"п„«","v":"7:180"},{"c":"п„¬","v":"7:180"}]},{"n":5,"w":[{"c":"п„®","v":"7:180"},{"c":"п„Ҝ","v":"7:180"},{"c":"п„°","v":"7:180"},{"c":"п„ұ","v":"7:180"},{"c":"п„І","v":"7:180","e":1},{"c":"п„і","v":"7:181"},{"c":"п„ҙ","v":"7:181"},{"c":"п„ө","v":"7:181"},{"c":"п„¶","v":"7:181"},{"c":"п„·","v":"7:181"}]},{"n":6,"w":[{"c":"п„ё","v":"7:181"},{"c":"п„№","v":"7:181"},{"c":"п„ә","v":"7:181","e":1},{"c":"п„»","v":"7:182"},{"c":"п„ј","v":"7:182"},{"c":"п„Ҫ","v":"7:182"},{"c":"п„ҫ","v":"7:182"}]},{"n":7,"w":[{"c":"п„ҝ","v":"7:182"},{"c":"п…Җ","v":"7:182"},{"c":"п…Ғ","v":"7:182"},{"c":"п…Ӯ","v":"7:182"},{"c":"п…ғ","v":"7:182","e":1},{"c":"п…„","v":"7:183"},{"c":"п……","v":"7:183"},{"c":"п…Ү","v":"7:183"},{"c":"п…Ҳ","v":"7:183"},{"c":"п…ү","v":"7:183"},{"c":"п…Ҡ","v":"7:183","e":1},{"c":"п…Ӣ","v":"7:184"}]},{"n":8,"w":[{"c":"п…Ң","v":"7:184"},{"c":"п…Һ","v":"7:184"},{"c":"п…Ҹ","v":"7:184"},{"c":"п…җ","v":"7:184"},{"c":"п…‘","v":"7:184"},{"c":"п…“","v":"7:184"},{"c":"п…”","v":"7:184"},{"c":"п…•","v":"7:184"},{"c":"п…–","v":"7:184"},{"c":"п…—","v":"7:184"},{"c":"п…ҳ","v":"7:184","e":1}]},{"n":9,"w":[{"c":"п…ҷ","v":"7:185"},{"c":"п…ҡ","v":"7:185"},{"c":"п…ӣ","v":"7:185"},{"c":"п…ң","v":"7:185"},{"c":"п…қ","v":"7:185"},{"c":"п…һ","v":"7:185"},{"c":"п…ҹ","v":"7:185"},{"c":"п… ","v":"7:185"},{"c":"п…Ў","v":"7:185"}]},{"n":10,"w":[{"c":"п…ў","v":"7:185"},{"c":"п…Ј","v":"7:185"},{"c":"п…Ө","v":"7:185"},{"c":"п…Ҙ","v":"7:185"},{"c":"п…Ұ","v":"7:185"},{"c":"п…§","v":"7:185"},{"c":"п…Ё","v":"7:185"},{"c":"п…©","v":"7:185"},{"c":"п…Ә","v":"7:185"},{"c":"п…¬","v":"7:185"},{"c":"п…ӯ","v":"7:185"}]},{"n":11,"w":[{"c":"п…®","v":"7:185"},{"c":"п…Ҝ","v":"7:185"},{"c":"п…°","v":"7:185","e":1},{"c":"п…ұ","v":"7:186"},{"c":"п…І","v":"7:186"},{"c":"п…і","v":"7:186"},{"c":"п…ҙ","v":"7:186"},{"c":"п…ө","v":"7:186"},{"c":"п…¶","v":"7:186"},{"c":"п…ё","v":"7:186"}]},{"n":12,"w":[{"c":"п…№","v":"7:186"},{"c":"п…ә","v":"7:186"},{"c":"п…»","v":"7:186"},{"c":"п…ј","v":"7:186","e":1},{"c":"п…Ҫ","v":"7:187"},{"c":"п…ҫ","v":"7:187"},{"c":"п…ҝ","v":"7:187"},{"c":"пҶҖ","v":"7:187"},{"c":"пҶҒ","v":"7:187"}]},{"n":13,"w":[{"c":"пҶғ","v":"7:187"},{"c":"пҶ„","v":"7:187"},{"c":"пҶ…","v":"7:187"},{"c":"пҶҶ","v":"7:187"},{"c":"пҶҮ","v":"7:187"},{"c":"пҶү","v":"7:187"},{"c":"пҶҠ","v":"7:187"},{"c":"пҶӢ","v":"7:187"},{"c":"пҶҢ","v":"7:187"},{"c":"пҶҚ","v":"7:187"},{"c":"пҶҸ","v":"7:187"},{"c":"пҶҗ","v":"7:187"}]},{"n":14,"w":[{"c":"пҶ‘","v":"7:187"},{"c":"пҶ’","v":"7:187"},{"c":"пҶ”","v":"7:187"},{"c":"пҶ•","v":"7:187"},{"c":"пҶ–","v":"7:187"},{"c":"пҶ—","v":"7:187"},{"c":"пҶҷ","v":"7:187"},{"c":"пҶҡ","v":"7:187"},{"c":"пҶӣ","v":"7:187"},{"c":"пҶң","v":"7:187"}]},{"n":15,"w":[{"c":"пҶһ","v":"7:187"},{"c":"пҶҹ","v":"7:187"},{"c":"пҶ ","v":"7:187"},{"c":"пҶЎ","v":"7:187"},{"c":"пҶў","v":"7:187"},{"c":"пҶЈ","v":"7:187"},{"c":"пҶӨ","v":"7:187"},{"c":"пҶҘ","v":"7:187"},{"c":"пҶҰ","v":"7:187"},{"c":"пҶ§","v":"7:187"},{"c":"пҶЁ","v":"7:187","e":1}]}]}